asyncvnc.py
asyncvnc-1.2.0.dist-info/LICENSE
asyncvnc-1.2.0.dist-info/METADATA
asyncvnc-1.2.0.dist-info/WHEEL
asyncvnc-1.2.0.dist-info/top_level.txt
asyncvnc-1.2.0.dist-info/RECORD
