Metadata-Version: 2.1
Name: asyncvnc
Version: 1.2.0
Summary: Asynchronous VNC for Python
Home-page: https://github.com/barneygale/asyncvnc
Author: Barney Gale
License: GPL
Platform: UNKNOWN
Requires-Python: >=3.7
License-File: LICENSE
Requires-Dist: cryptography
Requires-Dist: keysymdef
Requires-Dist: numpy
